croniter_rs/__init__.py
croniter_rs/croniter_rs.pypy311-pp73-x86-linux-gnu.so
croniter_rs-0.1.0.dist-info/METADATA
croniter_rs-0.1.0.dist-info/WHEEL
croniter_rs-0.1.0.dist-info/licenses/LICENSE
croniter_rs-0.1.0.dist-info/RECORD
