Metadata-Version: 2.4
Name: croniter_rs
Version: 0.1.0
Classifier: Development Status :: 4 - Beta
Classifier: Intended Audience :: Developers
Classifier: License :: OSI Approved :: MIT License
Classifier: Programming Language :: Rust
Classifier: Programming Language :: Python :: 3
Classifier: Programming Language :: Python :: 3.8
Classifier: Programming Language :: Python :: 3.9
Classifier: Programming Language :: Python :: 3.10
Classifier: Programming Language :: Python :: 3.11
Classifier: Programming Language :: Python :: 3.12
Classifier: Programming Language :: Python :: Implementation :: CPython
Classifier: Topic :: Software Development :: Libraries :: Python Modules
Classifier: Topic :: System :: Systems Administration
Requires-Dist: pytest>=7.0 ; extra == 'benchmark'
Requires-Dist: pytest-benchmark>=4.0 ; extra == 'benchmark'
Requires-Dist: croniter>=2.0 ; extra == 'benchmark'
Requires-Dist: pytest>=7.0 ; extra == 'dev'
Requires-Dist: pytest-benchmark>=4.0 ; extra == 'dev'
Requires-Dist: croniter>=2.0 ; extra == 'dev'
Requires-Dist: pytest>=7.0 ; extra == 'test'
Requires-Dist: croniter>=2.0 ; extra == 'test'
Provides-Extra: benchmark
Provides-Extra: dev
Provides-Extra: test
License-File: LICENSE
Summary: High-performance Rust implementation of Python croniter
Keywords: cron,schedule,croniter,rust,performance
Author: croniter-rs contributors
License: MIT
Requires-Python: >=3.8
Project-URL: Homepage, https://github.com/Souls-R/croniter-rs
Project-URL: Issues, https://github.com/Souls-R/croniter-rs/issues
Project-URL: Repository, https://github.com/Souls-R/croniter-rs
